menten_gcn/__init__.py
menten_gcn/data_maker.py
menten_gcn/data_management.py
menten_gcn/wrappers.py
menten_gcn/decorators/__init__.py
menten_gcn/decorators/base.py
menten_gcn/decorators/geometry.py
menten_gcn/decorators/rosetta.py
menten_gcn/decorators/sequence.py
menten_gcn/decorators/standard.py
menten_gcn/playground/__init__.py
menten_gcn/playground/nbody_convs.py
menten_gcn/published/__init__.py
menten_gcn/published/__init__.py~
menten_gcn/published/maguire_grattarola_2021.py
menten_gcn/published/published.py~
menten_gcn/tests/__init__.py
menten_gcn/util/__init__.py
menten_gcn/util/util.py
menten_gcn-0.4.0.dist-info/AUTHORS.rst
menten_gcn-0.4.0.dist-info/LICENSE
menten_gcn-0.4.0.dist-info/METADATA
menten_gcn-0.4.0.dist-info/WHEEL
menten_gcn-0.4.0.dist-info/top_level.txt
menten_gcn-0.4.0.dist-info/RECORD
